model_monitor/__init__.py
model_monitor/cli.py
model_monitor/config.py
model_monitor/monitor.py
model_monitor/alerting/__init__.py
model_monitor/alerting/notification.py
model_monitor/alerting/thresholds.py
model_monitor/data_drift/__init__.py
model_monitor/data_drift/distribution_metrics.py
model_monitor/data_drift/feature_drift.py
model_monitor/data_drift/statistical_tests.py
model_monitor/model_drift/__init__.py
model_monitor/model_drift/concept_drift.py
model_monitor/model_drift/performance_metrics.py
model_monitor/model_drift/prediction_drift.py
model_monitor/utils/__init__.py
model_monitor/utils/data_loader.py
model_monitor/utils/preprocessing.py
model_monitor/visualization/__init__.py
model_monitor/visualization/drift_plots.py
model_monitor-0.1.1.dist-info/LICENSE
model_monitor-0.1.1.dist-info/METADATA
model_monitor-0.1.1.dist-info/WHEEL
model_monitor-0.1.1.dist-info/entry_points.txt
model_monitor-0.1.1.dist-info/top_level.txt
model_monitor-0.1.1.dist-info/RECORD
